cxcli/__init__.py
cxcli/cli.py
cxcli/config.py
cxcli/exc.py
cxcli/services/__init__.py
cxcli/services/auth.py
cxcli/services/deployments.py
cxcli/services/predictions.py
cxcli/services/service.py
cxcli/services/users.py
pyproject.toml
computex_cli-0.2.0.dist-info/METADATA
computex_cli-0.2.0.dist-info/WHEEL
computex_cli-0.2.0.dist-info/entry_points.txt
computex_cli-0.2.0.dist-info/RECORD
