Metadata-Version: 2.1
Name: computex-cli
Version: 0.2.0
Summary: ComputeX CLI tool
Author: Abate De Mey
Author-email: abate@computex.ai
Requires-Python: >=3.8.1,<4.0.0
Classifier: Programming Language :: Python :: 3
Classifier: Programming Language :: Python :: 3.9
Classifier: Programming Language :: Python :: 3.10
Classifier: Programming Language :: Python :: 3.11
Requires-Dist: click (>=8.1.3,<9.0.0)
Requires-Dist: cryptography (>=41.0.1,<42.0.0)
Requires-Dist: docker (>=6.1.3,<7.0.0)
Requires-Dist: keyring (>=24.2.0,<25.0.0)
Requires-Dist: pydantic (>=1.10.9,<2.0.0)
Requires-Dist: pyjwt (>=2.7.0,<3.0.0)
Requires-Dist: python-dotenv (>=1.0.0,<2.0.0)
Requires-Dist: requests (>=2.31.0,<3.0.0)
Requires-Dist: toml (>=0.10.2,<0.11.0)
